pathquant/__init__.py
pathquant-0.0.dist-info/licenses/LICENSE
pathquant-0.0.dist-info/METADATA
pathquant-0.0.dist-info/WHEEL
pathquant-0.0.dist-info/top_level.txt
pathquant-0.0.dist-info/RECORD
